{
  "ComponentIndexes": {},
  "ControlUniqueIds": {
    "AddPicture5": 344,
    "AddPicture6": 231,
    "Aenderung_DataCard1": 463,
    "AlleAusgaben": 73,
    "AlleFahrten": 3,
    "App": 1,
    "Art_Column1": 300,
    "Art_DataCard4": 197,
    "Ausgabe_Art_DataCard1": 322,
    "AusgabenDetails": 184,
    "AusgabenGesamt": 287,
    "Auto_DataCard3": 66,
    "Auto_DataCard4": 137,
    "Belegbild_big": 234,
    "Belegbild_DataCard6": 340,
    "Belegbild_DataCard7": 227,
    "Betrag_Column1": 301,
    "Betrag_DataCard2": 528,
    "Betrag_DataCard3": 316,
    "Betrag_DataCard4": 204,
    "Body1": 81,
    "Body2": 15,
    "BrowseGallery2": 9,
    "but_buchen_1": 368,
    "but_buchen_2": 363,
    "but_buchen_3": 373,
    "but_buchen_5": 378,
    "but_buchen_6": 383,
    "but_buchen_7": 388,
    "but_buchen_8": 393,
    "but_buchen_9": 398,
    "butAendernSpeichern": 187,
    "butBack": 186,
    "butBehalten": 241,
    "butLoeschen": 242,
    "Button10": 510,
    "Button10_1": 511,
    "Button2": 516,
    "Button3": 538,
    "Button4": 275,
    "Button5": 442,
    "Button6": 403,
    "Button7": 497,
    "Button8": 494,
    "Button8_1": 495,
    "Button9": 243,
    "ButtonBack": 6,
    "ButtonBack_1": 173,
    "ButtonBack_2": 90,
    "ButtonBack_3": 445,
    "ButtonBack_4": 75,
    "ButtonBack_5": 505,
    "ButtonBack_6": 307,
    "ButtonBack_7": 281,
    "ButtonBack_8": 155,
    "ButtonBack_9": 410,
    "ButtonBackNF": 21,
    "ButtonBackNF_1": 262,
    "ButtonBackNF_2": 477,
    "ButtonKM": 286,
    "ButtonNew": 7,
    "ButtonNew_2": 92,
    "ButtonNew_4": 77,
    "ButtonNew_5": 308,
    "buttonPayPal": 291,
    "ButtonSave": 22,
    "ButtonSave_1": 263,
    "ButtonSave_2": 478,
    "ButtonSpend": 288,
    "CalendarEventsGallery1": 428,
    "Container Alle Fahrten": 364,
    "Container Neue Ausgabe": 374,
    "Container Neue Fahrt": 359,
    "Container Reservierung_4": 379,
    "Container Reservierung_5": 384,
    "Container Reservierung_6": 389,
    "Container Reservierung_7": 394,
    "Container Reservierungen": 369,
    "Container16": 365,
    "Container16_1": 367,
    "Container16_10": 380,
    "Container16_11": 382,
    "Container16_12": 385,
    "Container16_13": 387,
    "Container16_14": 390,
    "Container16_15": 392,
    "Container16_16": 395,
    "Container16_17": 397,
    "Container16_2": 360,
    "Container16_3": 362,
    "Container16_4": 370,
    "Container16_5": 372,
    "Container16_8": 375,
    "Container16_9": 377,
    "Container17": 358,
    "DataCardKey1": 221,
    "DataCardKey10": 28,
    "DataCardKey11": 58,
    "DataCardKey12": 338,
    "DataCardKey15": 525,
    "DataCardKey16": 455,
    "DataCardKey17": 530,
    "DataCardKey18": 460,
    "DataCardKey19": 535,
    "DataCardKey2": 325,
    "DataCardKey20": 465,
    "DataCardKey21": 68,
    "DataCardKey22": 139,
    "DataCardKey23": 471,
    "DataCardKey26": 342,
    "DataCardKey27": 144,
    "DataCardKey28": 229,
    "DataCardKey3": 33,
    "DataCardKey30": 96,
    "DataCardKey31": 103,
    "DataCardKey32": 107,
    "DataCardKey33": 148,
    "DataCardKey34": 313,
    "DataCardKey36": 318,
    "DataCardKey37": 329,
    "DataCardKey38": 334,
    "DataCardKey4": 38,
    "DataCardKey40": 112,
    "DataCardKey41": 118,
    "DataCardKey42": 193,
    "DataCardKey43": 199,
    "DataCardKey44": 206,
    "DataCardKey45": 211,
    "DataCardKey46": 216,
    "DataCardKey48": 129,
    "DataCardKey49": 124,
    "DataCardKey5": 44,
    "DataCardKey50": 134,
    "DataCardKey56": 247,
    "DataCardKey57": 251,
    "DataCardKey6": 225,
    "DataCardKey7": 54,
    "DataCardKey8": 63,
    "DataCardKey9": 48,
    "DataCardValue10": 536,
    "DataCardValue11": 531,
    "DataCardValue12": 466,
    "DataCardValue13": 140,
    "DataCardValue18": 145,
    "DataCardValue2": 339,
    "DataCardValue20": 149,
    "DataCardValue26": 97,
    "DataCardValue29": 113,
    "DataCardValue3": 222,
    "DataCardValue30": 119,
    "DataCardValue32": 248,
    "DataCardValue33": 252,
    "DataCardValue35": 330,
    "DataCardValue36": 335,
    "DataCardValue38": 130,
    "DataCardValue4": 226,
    "DataCardValue40": 194,
    "DataCardValue41": 200,
    "DataCardValue42": 207,
    "DataCardValue43": 212,
    "DataCardValue44": 217,
    "DataCardValue46": 135,
    "DataCardValue6": 526,
    "DataCardValue7": 69,
    "DataCardValue8": 456,
    "DataCardValue9": 461,
    "DataTable2": 298,
    "DataTableFahrten": 292,
    "DateValue1": 472,
    "Datum_Column1": 299,
    "Datum_DataCard1": 25,
    "Datum_DataCard2": 468,
    "Datum_DataCard3": 311,
    "Datum_DataCard4": 190,
    "Datum_DataCard7": 94,
    "DatumInput": 26,
    "Dropdown4": 201,
    "EndDatePicker": 272,
    "EndDatePicker_1": 490,
    "Ende_Column1": 295,
    "Ende_DataCard1": 35,
    "Ende_DataCard4": 105,
    "EndeInput": 36,
    "EndTimePicker": 271,
    "EndTimePicker_1": 489,
    "errorDatum": 315,
    "ErrorMessage1": 223,
    "ErrorMessage10": 60,
    "ErrorMessage12": 527,
    "ErrorMessage13": 532,
    "ErrorMessage14": 150,
    "ErrorMessage15": 253,
    "ErrorMessage16": 70,
    "ErrorMessage17": 141,
    "ErrorMessage18": 457,
    "ErrorMessage19": 462,
    "ErrorMessage2": 29,
    "ErrorMessage20": 537,
    "ErrorMessage21": 467,
    "ErrorMessage24": 345,
    "ErrorMessage25": 232,
    "ErrorMessage3": 34,
    "ErrorMessage30": 99,
    "ErrorMessage32": 104,
    "ErrorMessage33": 109,
    "ErrorMessage34": 321,
    "ErrorMessage35": 331,
    "ErrorMessage36": 336,
    "ErrorMessage37": 115,
    "ErrorMessage38": 121,
    "ErrorMessage39": 131,
    "ErrorMessage4": 39,
    "ErrorMessage40": 196,
    "ErrorMessage41": 203,
    "ErrorMessage42": 208,
    "ErrorMessage43": 213,
    "ErrorMessage44": 218,
    "ErrorMessage45": 126,
    "ErrorMessage46": 136,
    "ErrorMessage5": 45,
    "ErrorMessage6": 326,
    "ErrorMessage7": 56,
    "ErrorMessage8": 65,
    "ErrorMessage9": 51,
    "Fahrdatum_Column1": 293,
    "Fahrer_DataCard1": 52,
    "Fahrer_DataCard4": 122,
    "FahrerInput": 55,
    "FahrtenDetails": 88,
    "Form1": 24,
    "Form2": 522,
    "Form3": 189,
    "Form4": 310,
    "Form5": 452,
    "Form6": 93,
    "FormViewer2": 245,
    "Gallery1": 78,
    "Gallery2": 176,
    "Gallery3": 517,
    "galleryTemplate1": 79,
    "galleryTemplate1_1": 418,
    "galleryTemplate2": 10,
    "galleryTemplate2_1": 421,
    "galleryTemplate3": 177,
    "galleryTemplate3_1": 429,
    "galleryTemplate4": 518,
    "Geändert am_DataCard2": 143,
    "Geändert am_DataCard3": 246,
    "Geändert von_DataCard3": 146,
    "Geändert von_DataCard4": 249,
    "Group3": 439,
    "GroupHeader": 18,
    "GroupHeader_1": 152,
    "GroupHeader_10": 513,
    "GroupHeader_2": 72,
    "GroupHeader_3": 87,
    "GroupHeader_4": 183,
    "GroupHeader_5": 347,
    "GroupHeader_6": 278,
    "GroupHeader_7": 170,
    "GroupHeader_8": 499,
    "GroupHeader_9": 474,
    "GroupHeader4": 304,
    "GroupHeaderStart": 405,
    "grpBelegBildGross": 258,
    "grpFehler": 277,
    "grpFehler_1": 500,
    "grpHeader": 257,
    "grpSicherheitsabfrage": 259,
    "grpWarnungLoeschen": 501,
    "Gruppe_DataCard1": 57,
    "Gruppe_DataCard3": 327,
    "Gruppe_DataCard4": 209,
    "Gruppe_DataCard6": 127,
    "GruppeInput": 59,
    "icoBusy": 424,
    "icoError": 492,
    "Icon1": 157,
    "Icon1_1": 411,
    "Icon10": 352,
    "Icon2": 13,
    "Icon3": 540,
    "Icon4": 273,
    "Icon5": 83,
    "Icon7": 174,
    "Icon8": 447,
    "Icon9": 400,
    "iconArt": 236,
    "iconCompress": 255,
    "iconEnlarge": 254,
    "iconNextMonth1": 415,
    "iconPrevMonth1": 413,
    "icoSelected": 423,
    "icoStart": 425,
    "Image11": 412,
    "Image13": 354,
    "Image15": 82,
    "Image24": 343,
    "Image26": 230,
    "Image5_1": 366,
    "Image5_2": 361,
    "Image5_3": 371,
    "Image5_5": 376,
    "Image5_6": 381,
    "Image5_7": 386,
    "Image5_8": 391,
    "Image5_9": 396,
    "Image7": 351,
    "Image7_1": 283,
    "Image9": 431,
    "Index_DataCard1": 219,
    "Index_DataCard3": 458,
    "inpEnde": 108,
    "inpFahrer": 125,
    "inpStart": 101,
    "InputArt": 323,
    "InputBetrag": 319,
    "InputDatum": 314,
    "KMKosten": 285,
    "Kommentar_DataCard1": 61,
    "Kommentar_DataCard3": 132,
    "KommentarInput": 64,
    "Konto": 279,
    "Kontostand": 290,
    "Kosten_Column1": 297,
    "Kosten_DataCard1": 46,
    "Kosten_DataCard4": 116,
    "labBuchungGruppe": 266,
    "labBuchungGruppe_1": 481,
    "labDay": 422,
    "Label1": 161,
    "Label1_1": 433,
    "Label1_3": 435,
    "Label10": 188,
    "Label11": 507,
    "Label12": 484,
    "Label12_1": 487,
    "Label13": 42,
    "Label13_1": 50,
    "Label14": 350,
    "Label15": 353,
    "Label15_1": 8,
    "Label15_2": 506,
    "Label16": 491,
    "Label17": 237,
    "Label18": 195,
    "Label19": 441,
    "Label2": 164,
    "Label20": 191,
    "Label21": 202,
    "Label22": 284,
    "Label23": 98,
    "Label24": 114,
    "Label25": 120,
    "Label25_2": 289,
    "Label26": 416,
    "Label27": 238,
    "Label28": 239,
    "Label28_1": 240,
    "Label29": 274,
    "Label3": 160,
    "Label30": 448,
    "Label31": 449,
    "Label32": 450,
    "Label33": 451,
    "Label34": 508,
    "Label38": 496,
    "Label4": 167,
    "Label5": 163,
    "Label6": 166,
    "Label7": 179,
    "Label7_1": 515,
    "Label8": 401,
    "Label8_2": 158,
    "Label8_3": 159,
    "Label9": 402,
    "labEnde": 270,
    "labEnde_1": 488,
    "labError": 493,
    "labGruppe": 265,
    "labGruppe_1": 480,
    "labKMStand": 355,
    "labKMStand_1": 357,
    "labKosten": 49,
    "labStart": 267,
    "labStart_1": 482,
    "labStrecke": 41,
    "labVersion": 404,
    "labVersion_1": 71,
    "labVersion_10": 169,
    "labVersion_11": 539,
    "labVersion_12": 182,
    "labVersion_13": 473,
    "labVersion_14": 512,
    "labVersion_2": 17,
    "labVersion_3": 438,
    "labVersion_4": 276,
    "labVersion_5": 498,
    "labVersion_6": 86,
    "labVersion_7": 256,
    "labVersion_8": 346,
    "labVersion_9": 303,
    "LblAppName1": 409,
    "LblAppName2": 5,
    "LblAppName2_1": 175,
    "LblAppName2_10": 264,
    "LblAppName2_11": 479,
    "LblAppName2_2": 446,
    "LblAppName2_3": 91,
    "LblAppName2_4": 23,
    "LblAppName2_5": 76,
    "LblAppName2_6": 504,
    "LblAppName2_7": 309,
    "LblAppName2_8": 282,
    "LblAppName2_9": 156,
    "LblCalendarEventsHeader1": 427,
    "LblMonthSelected1": 414,
    "LblNoEvents1": 437,
    "MonthDayGallery1": 420,
    "Name_DataCard1": 224,
    "Name_DataCard2": 523,
    "Name_DataCard3": 337,
    "NeueAusgabe": 305,
    "NeueFahrt": 19,
    "Ort_Column1": 302,
    "Ort_DataCard3": 332,
    "Ort_DataCard4": 214,
    "popupVersionsupdate": 406,
    "recHintergrund": 235,
    "Rectangle1": 14,
    "Rectangle2": 162,
    "Rectangle2_1": 165,
    "Rectangle2_2": 168,
    "Rectangle3": 349,
    "Rectangle4": 185,
    "Rectangle5": 483,
    "Rectangle6": 233,
    "Rectangle7": 399,
    "Rectangle8": 356,
    "RectCalendarEventsHeader1": 426,
    "RectQuickActionBar1": 408,
    "RectQuickActionBar2": 4,
    "RectQuickActionBar2_1": 172,
    "RectQuickActionBar2_10": 476,
    "RectQuickActionBar2_11": 444,
    "RectQuickActionBar2_2": 89,
    "RectQuickActionBar2_3": 20,
    "RectQuickActionBar2_4": 74,
    "RectQuickActionBar2_5": 503,
    "RectQuickActionBar2_6": 306,
    "RectQuickActionBar2_7": 280,
    "RectQuickActionBar2_8": 154,
    "RectQuickActionBar2_9": 261,
    "ScreenBuchungAendern": 475,
    "ScreenFahrzeug": 502,
    "ScreenKalender": 407,
    "ScreenNeueBuchung": 260,
    "ScreenNeueBuchungDoku": 440,
    "ScreenVersionen": 171,
    "ScreenVersionenNeu": 443,
    "Separator1": 244,
    "Separator1_1": 151,
    "Separator2": 85,
    "Separator3": 16,
    "Separator3_1": 436,
    "Separator4": 521,
    "Separator5": 469,
    "Separator6": 181,
    "Settings": 514,
    "Start": 348,
    "Start_Column1": 294,
    "Start_DataCard1": 30,
    "Start_DataCard4": 100,
    "StartDatePicker": 268,
    "StartDatePicker_1": 485,
    "StartInput": 31,
    "StartTimePicker": 269,
    "StartTimePicker_1": 486,
    "StarVisible1": 47,
    "StarVisible10": 524,
    "StarVisible11": 529,
    "StarVisible12": 147,
    "StarVisible13": 250,
    "StarVisible14": 67,
    "StarVisible15": 138,
    "StarVisible16": 454,
    "StarVisible17": 459,
    "StarVisible18": 534,
    "StarVisible19": 464,
    "StarVisible2": 220,
    "StarVisible20": 470,
    "StarVisible23": 341,
    "StarVisible24": 228,
    "StarVisible29": 95,
    "StarVisible3": 32,
    "StarVisible3_2": 27,
    "StarVisible3_3": 192,
    "StarVisible3_4": 198,
    "StarVisible3_5": 205,
    "StarVisible3_6": 312,
    "StarVisible3_8": 317,
    "StarVisible30": 102,
    "StarVisible31": 106,
    "StarVisible32": 328,
    "StarVisible33": 333,
    "StarVisible35": 111,
    "StarVisible36": 117,
    "StarVisible37": 128,
    "StarVisible38": 123,
    "StarVisible39": 133,
    "StarVisible4": 37,
    "StarVisible40": 210,
    "StarVisible41": 215,
    "StarVisible5": 43,
    "StarVisible6": 324,
    "StarVisible7": 53,
    "StarVisible8": 62,
    "Statistiken": 153,
    "Strecke_Column1": 296,
    "Strecke_DataCard1": 40,
    "Strecke_DataCard4": 110,
    "Subtitle2": 84,
    "Subtitle3": 12,
    "Subtitle3_1": 432,
    "Subtitle3_2": 434,
    "Subtitle4": 520,
    "Subtitle5": 180,
    "TextInput2": 509,
    "TextInput3": 320,
    "Title1": 419,
    "Title2": 80,
    "Title3": 11,
    "Title4": 519,
    "Title5": 178,
    "Title7": 430,
    "version_DataCard1": 453,
    "ViewAenderungsdaten": 142,
    "WeekdayGallery1": 417,
    "Wert_DataCard1": 533
  },
  "FunctionParamsInvariantScripts": {},
  "HeaderLastSavedDateTimeUTC": "01/17/2022 16:03:15",
  "LocalDatabaseReferencesAsEmpty": false,
  "LocalResourceFileNames": {
    "001-wallet": "0016.svg",
    "002-accounting": "0010.svg",
    "002-money-transfer": "0012.svg",
    "003-car-wash": "0014.svg",
    "004-maintenance": "0013.svg",
    "005-parking": "0015.svg",
    "006-calendar": "0020.svg",
    "007-calendar-1": "0024.png",
    "bg ford 812": "0003.png",
    "car-driver blau": "0021.png",
    "car-statistics": "0007.svg",
    "car-wheel": "0026.png",
    "checkout-logo-150x32-alt-2x": "0019.png",
    "datei": "0027.png",
    "gas-station": "0009.svg",
    "ico_alleausgaben": "9f291dff-a59e-4ae4-8f70-70ab4eed13d9.png",
    "ico_allefahrten": "437d36f0-706f-40e2-998a-76e40e5e8fca.png",
    "ico_buchenNeu": "7f34dd97-b025-47f6-93ff-a7b1509d8973.png",
    "ico_fahrerin": "b6b7739d-21e0-4ece-8ed0-b968b3564cea.png",
    "ico_fahrten": "6f847874-647f-45b3-8918-cebce4699819.png",
    "ico_fahrzeug": "949adeb1-0729-482f-bc30-c992bddc252d.png",
    "ico_konto": "f3af2a58-179d-4cfa-bf4d-54ea5ee007d6.png",
    "ico_neueausgaben": "fff5a343-db15-4bb4-a88e-a1ccf0001210.png",
    "ico_stats": "878b3f5e-574d-406b-b73f-b31240c6fc19.png",
    "marketing": "0011.svg",
    "riding-car": "0006.svg"
  },
  "LocalResourceRootPaths": {
    "001-wallet": "https://docserverpwaprodweu.blob.core.windows.net/37996848-e161-4c4d-8634-0f16fc915d5c-1/resource/Assets0Images00016.svg?sv=2017-04-17&sr=b&sig=DRF69bTBmLY8mZIOXzvCOHdpLT91bpu3ntBoXyT5w1w%3D&spr=https&se=2022-01-18T16%3A15%3A30Z&sp=r",
    "002-accounting": "https://docserverpwaprodweu.blob.core.windows.net/37996848-e161-4c4d-8634-0f16fc915d5c-1/resource/Assets0Images00010.svg?sv=2017-04-17&sr=b&sig=Ly5bD8Co2%2B5jIzCSrgEnCdKCT1mXPJ2jNvqesrdQaOE%3D&spr=https&se=2022-01-18T16%3A15%3A30Z&sp=r",
    "002-money-transfer": "https://docserverpwaprodweu.blob.core.windows.net/37996848-e161-4c4d-8634-0f16fc915d5c-1/resource/Assets0Images00012.svg?sv=2017-04-17&sr=b&sig=exEv%2BZhJCS%2BKZGICHJk23XFDxvEuUXOqXlbEkfbiMQ4%3D&spr=https&se=2022-01-18T16%3A15%3A30Z&sp=r",
    "003-car-wash": "https://docserverpwaprodweu.blob.core.windows.net/37996848-e161-4c4d-8634-0f16fc915d5c-1/resource/Assets0Images00014.svg?sv=2017-04-17&sr=b&sig=xoyImJMOJVWuDzMuLjgi73PpGAK94q3igXHv34W2hb0%3D&spr=https&se=2022-01-18T16%3A15%3A30Z&sp=r",
    "004-maintenance": "https://docserverpwaprodweu.blob.core.windows.net/37996848-e161-4c4d-8634-0f16fc915d5c-1/resource/Assets0Images00013.svg?sv=2017-04-17&sr=b&sig=RtcRe%2F6k668CiOdTapMAc8PTpn%2FZqcsTndEu6%2FnlBwY%3D&spr=https&se=2022-01-18T16%3A15%3A30Z&sp=r",
    "005-parking": "https://docserverpwaprodweu.blob.core.windows.net/37996848-e161-4c4d-8634-0f16fc915d5c-1/resource/Assets0Images00015.svg?sv=2017-04-17&sr=b&sig=6fnRGwck6zzZqewpqFroKnVt2Y%2BeoBG3G1%2FF1zHxyeA%3D&spr=https&se=2022-01-18T16%3A15%3A30Z&sp=r",
    "006-calendar": "https://docserverpwaprodweu.blob.core.windows.net/37996848-e161-4c4d-8634-0f16fc915d5c-1/resource/Assets0Images00020.svg?sv=2017-04-17&sr=b&sig=vKhUi1EbJqnD%2Fj408NDLWBGWtRLJiZ5aMTuZdNLSSHM%3D&spr=https&se=2022-01-18T16%3A15%3A30Z&sp=r",
    "007-calendar-1": "https://docserverpwaprodweu.blob.core.windows.net/37996848-e161-4c4d-8634-0f16fc915d5c-1/resource/Assets0Images00024.png?sv=2017-04-17&sr=b&sig=hRM2hz3Sdszvoz7oOMpLdLaugy0RAg05mfEcjL8D2l0%3D&spr=https&se=2022-01-18T16%3A15%3A30Z&sp=r",
    "bg ford 812": "https://docserverpwaprodweu.blob.core.windows.net/37996848-e161-4c4d-8634-0f16fc915d5c-1/resource/Assets0Images00003.png?sv=2017-04-17&sr=b&sig=ooQqgF4wgc%2FBmidtXNAO14srbzRjpbfBVdLeMCzLDQ8%3D&spr=https&se=2022-01-18T16%3A15%3A30Z&sp=r",
    "car-driver blau": "https://docserverpwaprodweu.blob.core.windows.net/37996848-e161-4c4d-8634-0f16fc915d5c-1/resource/Assets0Images00021.png?sv=2017-04-17&sr=b&sig=e6aYOFLiSnV5v4zEVKCrDQVSewQ7HtyO468JSUIGgaI%3D&spr=https&se=2022-01-18T16%3A15%3A30Z&sp=r",
    "car-statistics": "https://docserverpwaprodweu.blob.core.windows.net/37996848-e161-4c4d-8634-0f16fc915d5c-1/resource/Assets0Images00007.svg?sv=2017-04-17&sr=b&sig=Hlh6iCc8E%2B8XgadEIlI0BHm%2FZdSSEF0Db8fuCZawBnk%3D&spr=https&se=2022-01-18T16%3A15%3A30Z&sp=r",
    "car-wheel": "https://docserverpwaprodweu.blob.core.windows.net/37996848-e161-4c4d-8634-0f16fc915d5c-1/resource/Assets0Images00026.png?sv=2017-04-17&sr=b&sig=C2%2B%2FVcAz4J0HLadhVVEZaofzVkyHAsEA2T%2FfWaORz%2FE%3D&spr=https&se=2022-01-18T16%3A15%3A30Z&sp=r",
    "checkout-logo-150x32-alt-2x": "https://docserverpwaprodweu.blob.core.windows.net/37996848-e161-4c4d-8634-0f16fc915d5c-1/resource/Assets0Images00019.png?sv=2017-04-17&sr=b&sig=NsVNEyi7L3xJE7OEZ7yJ8w%2BIxd215Dj2hHCEDuYq9JE%3D&spr=https&se=2022-01-18T16%3A15%3A30Z&sp=r",
    "datei": "https://docserverpwaprodweu.blob.core.windows.net/37996848-e161-4c4d-8634-0f16fc915d5c-1/resource/Assets0Images00027.png?sv=2017-04-17&sr=b&sig=YGhMk3GqiD4vvHB6BgQ3sxEkWhdmDP0czte%2BbB%2FfiL8%3D&spr=https&se=2022-01-18T16%3A15%3A30Z&sp=r",
    "gas-station": "https://docserverpwaprodweu.blob.core.windows.net/37996848-e161-4c4d-8634-0f16fc915d5c-1/resource/Assets0Images00009.svg?sv=2017-04-17&sr=b&sig=0YRVjU02U2lWbg4JCsDT%2B5lDoiAW9nvL62rsSJt2scs%3D&spr=https&se=2022-01-18T16%3A15%3A30Z&sp=r",
    "ico_alleausgaben": "https://docserverpwaprodweu.blob.core.windows.net/37996848-e161-4c4d-8634-0f16fc915d5c-1/resource/Assets0Images09f291dff-a59e-4ae4-8f70-70ab4eed13d9.png?sv=2017-04-17&sr=b&sig=QmzINoP2InSqxV3hS4NE3aIk3y5OUP58jdayM3IjAis%3D&spr=https&se=2022-01-18T16%3A15%3A30Z&sp=r",
    "ico_allefahrten": "https://docserverpwaprodweu.blob.core.windows.net/37996848-e161-4c4d-8634-0f16fc915d5c-1/resource/Assets0Images0437d36f0-706f-40e2-998a-76e40e5e8fca.png?sv=2017-04-17&sr=b&sig=gkuIzvE6xFQwPs5O5w1Oc6ui1qjZK6cl6a9jg5ty4I0%3D&spr=https&se=2022-01-18T16%3A15%3A30Z&sp=r",
    "ico_buchenNeu": "https://docserverpwaprodweu.blob.core.windows.net/37996848-e161-4c4d-8634-0f16fc915d5c-1/resource/Assets0Images07f34dd97-b025-47f6-93ff-a7b1509d8973.png?sv=2017-04-17&sr=b&sig=6ooI9O4GiUdP%2B0eofNWyF1PmZKCQQCfygP%2FXn7K8Sq0%3D&spr=https&se=2022-01-18T16%3A15%3A30Z&sp=r",
    "ico_fahrerin": "https://docserverpwaprodweu.blob.core.windows.net/37996848-e161-4c4d-8634-0f16fc915d5c-1/resource/Assets0Images0b6b7739d-21e0-4ece-8ed0-b968b3564cea.png?sv=2017-04-17&sr=b&sig=DBrcmjTkcQlLihpmR8OtQ0Xot%2BDgBS8tTlTN86ZiN3c%3D&spr=https&se=2022-01-18T16%3A15%3A30Z&sp=r",
    "ico_fahrten": "https://docserverpwaprodweu.blob.core.windows.net/37996848-e161-4c4d-8634-0f16fc915d5c-1/resource/Assets0Images06f847874-647f-45b3-8918-cebce4699819.png?sv=2017-04-17&sr=b&sig=qEIFdMCTHXNXWEl6YqRopucNxWiAuSvjNayc%2FXrmNX8%3D&spr=https&se=2022-01-18T16%3A15%3A30Z&sp=r",
    "ico_fahrzeug": "https://docserverpwaprodweu.blob.core.windows.net/37996848-e161-4c4d-8634-0f16fc915d5c-1/resource/Assets0Images0949adeb1-0729-482f-bc30-c992bddc252d.png?sv=2017-04-17&sr=b&sig=aeJ%2B%2FMwW3oAO6twsJvXl0XON001AuEC7r9LZ1uuFPS4%3D&spr=https&se=2022-01-18T16%3A15%3A30Z&sp=r",
    "ico_konto": "https://docserverpwaprodweu.blob.core.windows.net/37996848-e161-4c4d-8634-0f16fc915d5c-1/resource/Assets0Images0f3af2a58-179d-4cfa-bf4d-54ea5ee007d6.png?sv=2017-04-17&sr=b&sig=oCg8pRqjFyfEbWUtTNKpbMe1eu2xXMreoMNnAwV%2Bz9w%3D&spr=https&se=2022-01-18T16%3A15%3A30Z&sp=r",
    "ico_neueausgaben": "https://docserverpwaprodweu.blob.core.windows.net/37996848-e161-4c4d-8634-0f16fc915d5c-1/resource/Assets0Images0fff5a343-db15-4bb4-a88e-a1ccf0001210.png?sv=2017-04-17&sr=b&sig=saf0IckUnUykrcVAkbLK2F%2FgC3CdJ5%2Fd8Y2wmcdADyo%3D&spr=https&se=2022-01-18T16%3A15%3A30Z&sp=r",
    "ico_stats": "https://docserverpwaprodweu.blob.core.windows.net/37996848-e161-4c4d-8634-0f16fc915d5c-1/resource/Assets0Images0878b3f5e-574d-406b-b73f-b31240c6fc19.png?sv=2017-04-17&sr=b&sig=B5qz%2Bhwf6XJ4kgn%2Fox4ddrIpf816TVu48A8eyWdAqLI%3D&spr=https&se=2022-01-18T16%3A15%3A30Z&sp=r",
    "marketing": "https://docserverpwaprodweu.blob.core.windows.net/37996848-e161-4c4d-8634-0f16fc915d5c-1/resource/Assets0Images00011.svg?sv=2017-04-17&sr=b&sig=HI%2FDcqlFax8y0mlBkAbX8gNsdArJ0QtaCZ4Mdt2xgRs%3D&spr=https&se=2022-01-18T16%3A15%3A30Z&sp=r",
    "riding-car": "https://docserverpwaprodweu.blob.core.windows.net/37996848-e161-4c4d-8634-0f16fc915d5c-1/resource/Assets0Images00006.svg?sv=2017-04-17&sr=b&sig=YVztp4ZCPmMCLCLthho4sJ3Xf78KDV7853cv83onyYY%3D&spr=https&se=2022-01-18T16%3A15%3A30Z&sp=r"
  },
  "OldLogoFileName": "rxbjznah.jpg",
  "OrderComponentMetadata": {},
  "OrderComponentTemplate": {},
  "OrderDataSource": {
    "Ausgaben": 44,
    "Ausgaben\\creb3_ausgabe_statecode": 26,
    "Ausgaben\\creb3_ausgabe_statuscode": 27,
    "Ausgaben\\creb3_ausgabeart": 25,
    "Ausgaben\\default.cds_creb3_ausgabe_views": 34,
    "Benutzer": 41,
    "Benutzer\\default.cds_systemuser_views": 37,
    "Benutzer\\systemuser_accessmode": 19,
    "Benutzer\\systemuser_address1_addresstypecode": 10,
    "Benutzer\\systemuser_address1_shippingmethodcode": 11,
    "Benutzer\\systemuser_address2_addresstypecode": 21,
    "Benutzer\\systemuser_address2_shippingmethodcode": 24,
    "Benutzer\\systemuser_azurestate": 22,
    "Benutzer\\systemuser_caltype": 20,
    "Benutzer\\systemuser_defaultfilterspopulated": 5,
    "Benutzer\\systemuser_deletestate": 16,
    "Benutzer\\systemuser_displayinserviceviews": 4,
    "Benutzer\\systemuser_emailrouteraccessapproval": 15,
    "Benutzer\\systemuser_incomingemaildeliverymethod": 18,
    "Benutzer\\systemuser_invitestatuscode": 23,
    "Benutzer\\systemuser_isactivedirectoryuser": 3,
    "Benutzer\\systemuser_isdisabled": 9,
    "Benutzer\\systemuser_isemailaddressapprovedbyo365admin": 7,
    "Benutzer\\systemuser_isintegrationuser": 6,
    "Benutzer\\systemuser_isuserlicensed": 2,
    "Benutzer\\systemuser_isusersynced": 8,
    "Benutzer\\systemuser_outgoingemaildeliverymethod": 13,
    "Benutzer\\systemuser_preferredaddresscode": 17,
    "Benutzer\\systemuser_preferredemailcode": 12,
    "Benutzer\\systemuser_preferredphonecode": 14,
    "Benutzer\\systemuser_setupuser": 1,
    "Bilder": 54,
    "ColumnChartSample": 42,
    "ComboBoxSample": 40,
    "CustomGallerySample": 39,
    "DropDownSample": 46,
    "Fahrten": 47,
    "Fahrten\\creb3_fahrten_statecode": 30,
    "Fahrten\\creb3_fahrten_statuscode": 31,
    "Fahrten\\default.cds_creb3_fahrten_views": 35,
    "HoursList": 55,
    "LegendSample": 43,
    "ListboxSample": 48,
    "myAusgaben": 51,
    "MyCalendarEvents": 57,
    "myFahrten": 50,
    "mySteuerdaten": 52,
    "myVersionen": 53,
    "Office365Outlook": 0,
    "Steuerdaten": 45,
    "Steuerdaten\\creb3_steuerdatum_statecode": 28,
    "Steuerdaten\\creb3_steuerdatum_statuscode": 29,
    "Steuerdaten\\default.cds_creb3_steuerdatum_views": 36,
    "Versionen": 49,
    "Versionen\\creb3_version_statecode": 32,
    "Versionen\\creb3_version_statuscode": 33,
    "Versionen\\default.cds_creb3_version_views": 38,
    "WochenTage": 56
  },
  "OrderGroupControls": {
    "Group3": {
      "Image11": 0,
      "Label26": 1
    },
    "GroupHeader": {
      "ButtonBack": 0,
      "ButtonNew": 3,
      "Label15_1": 2,
      "LblAppName2": 1,
      "RectQuickActionBar2": 4
    },
    "GroupHeader_1": {
      "ButtonBack_2": 0,
      "ButtonNew_2": 2,
      "LblAppName2_3": 1,
      "RectQuickActionBar2_2": 3
    },
    "GroupHeader_10": {
      "ButtonBack_5": 0,
      "Label15_2": 2,
      "LblAppName2_6": 1,
      "RectQuickActionBar2_5": 3
    },
    "GroupHeader_2": {
      "ButtonBackNF": 0,
      "ButtonSave": 2,
      "LblAppName2_4": 1,
      "RectQuickActionBar2_3": 3
    },
    "GroupHeader_3": {
      "ButtonBack_4": 0,
      "ButtonNew_4": 2,
      "LblAppName2_5": 1,
      "RectQuickActionBar2_4": 3
    },
    "GroupHeader_4": {
      "ButtonBack_1": 0,
      "LblAppName2_1": 1,
      "RectQuickActionBar2_1": 2
    },
    "GroupHeader_5": {
      "ButtonBack_6": 0,
      "ButtonNew_5": 2,
      "LblAppName2_7": 1,
      "RectQuickActionBar2_6": 3
    },
    "GroupHeader_6": {
      "ButtonBackNF_1": 0,
      "ButtonSave_1": 2,
      "LblAppName2_10": 1,
      "RectQuickActionBar2_9": 3
    },
    "GroupHeader_7": {
      "ButtonBack_8": 0,
      "LblAppName2_9": 1,
      "RectQuickActionBar2_8": 2
    },
    "GroupHeader_8": {
      "ButtonBackNF_2": 0,
      "ButtonSave_2": 2,
      "LblAppName2_11": 1,
      "RectQuickActionBar2_10": 3
    },
    "GroupHeader_9": {
      "ButtonBack_3": 0,
      "LblAppName2_2": 1,
      "RectQuickActionBar2_11": 2
    },
    "GroupHeader4": {
      "ButtonBack_7": 1,
      "Image7_1": 2,
      "LblAppName2_8": 0,
      "RectQuickActionBar2_7": 3
    },
    "GroupHeaderStart": {
      "Image7": 3,
      "Label14": 1,
      "Label15": 0,
      "Rectangle3": 2
    },
    "grpBelegBildGross": {
      "Belegbild_big": 1,
      "Rectangle6": 0
    },
    "grpFehler": {
      "Icon4": 0,
      "Label29": 1
    },
    "grpFehler_1": {
      "icoError": 0,
      "labError": 1
    },
    "grpHeader": {
      "butAendernSpeichern": 1,
      "butBack": 0,
      "Label10": 2,
      "Rectangle4": 3
    },
    "grpSicherheitsabfrage": {
      "butBehalten": 4,
      "butLoeschen": 5,
      "Label17": 0,
      "Label27": 1,
      "Label28": 2,
      "Label28_1": 3,
      "recHintergrund": 6
    },
    "grpWarnungLoeschen": {
      "Button8": 1,
      "Button8_1": 0,
      "Label12": 4,
      "Label12_1": 3,
      "Label16": 2,
      "Rectangle5": 5
    },
    "popupVersionsupdate": {
      "Button6": 2,
      "Label8": 0,
      "Label9": 1,
      "Rectangle7": 3
    }
  },
  "OrderTemplate": {},
  "OrderXMLTemplate": {
    "addMedia": 12,
    "button": 2,
    "circle": 14,
    "combobox": 10,
    "datepicker": 6,
    "dropdown": 11,
    "form": 5,
    "formViewer": 9,
    "gallery": 3,
    "groupContainer": 13,
    "icon": 4,
    "image": 8,
    "label": 1,
    "rectangle": 0,
    "text": 7
  },
  "PublishOrderIndices": {
    "AddPicture5": 397,
    "AddPicture6": 332,
    "Aenderung_DataCard1": 499,
    "AlleAusgaben": 0,
    "AlleFahrten": 0,
    "App": 0,
    "Art_Column1": 421,
    "Art_DataCard4": 298,
    "Ausgabe_Art_DataCard1": 375,
    "AusgabenDetails": 0,
    "AusgabenGesamt": 408,
    "Auto_DataCard3": 106,
    "Auto_DataCard4": 176,
    "Belegbild_big": 335,
    "Belegbild_DataCard6": 393,
    "Belegbild_DataCard7": 328,
    "Betrag_Column1": 422,
    "Betrag_DataCard2": 455,
    "Betrag_DataCard3": 369,
    "Betrag_DataCard4": 305,
    "Body1": 277,
    "Body2": 124,
    "BrowseGallery2": 118,
    "but_buchen_1": 21,
    "but_buchen_2": 16,
    "but_buchen_3": 26,
    "but_buchen_5": 31,
    "but_buchen_6": 36,
    "but_buchen_7": 41,
    "but_buchen_8": 46,
    "but_buchen_9": 51,
    "butAendernSpeichern": 285,
    "butBack": 284,
    "butBehalten": 342,
    "butLoeschen": 343,
    "Button10": 518,
    "Button10_1": 519,
    "Button2": 443,
    "Button3": 465,
    "Button4": 239,
    "Button5": 242,
    "Button6": 57,
    "Button7": 267,
    "Button8": 264,
    "Button8_1": 265,
    "Button9": 344,
    "ButtonBack": 114,
    "ButtonBack_1": 468,
    "ButtonBack_2": 128,
    "ButtonBack_3": 480,
    "ButtonBack_4": 270,
    "ButtonBack_5": 512,
    "ButtonBack_6": 359,
    "ButtonBack_7": 401,
    "ButtonBack_8": 426,
    "ButtonBack_9": 193,
    "ButtonBackNF": 60,
    "ButtonBackNF_1": 224,
    "ButtonBackNF_2": 244,
    "ButtonKM": 407,
    "ButtonNew": 115,
    "ButtonNew_2": 130,
    "ButtonNew_4": 272,
    "ButtonNew_5": 360,
    "buttonPayPal": 412,
    "ButtonSave": 61,
    "ButtonSave_1": 225,
    "ButtonSave_2": 245,
    "ButtonSpend": 409,
    "CalendarEventsGallery1": 212,
    "Container Alle Fahrten": 17,
    "Container Neue Ausgabe": 27,
    "Container Neue Fahrt": 12,
    "Container Reservierung_4": 32,
    "Container Reservierung_5": 37,
    "Container Reservierung_6": 42,
    "Container Reservierung_7": 47,
    "Container Reservierungen": 22,
    "Container16": 18,
    "Container16_1": 20,
    "Container16_10": 33,
    "Container16_11": 35,
    "Container16_12": 38,
    "Container16_13": 40,
    "Container16_14": 43,
    "Container16_15": 45,
    "Container16_16": 48,
    "Container16_17": 50,
    "Container16_2": 13,
    "Container16_3": 15,
    "Container16_4": 23,
    "Container16_5": 25,
    "Container16_8": 28,
    "Container16_9": 30,
    "Container17": 11,
    "DataCardKey1": 322,
    "DataCardKey10": 68,
    "DataCardKey11": 98,
    "DataCardKey12": 391,
    "DataCardKey15": 452,
    "DataCardKey16": 491,
    "DataCardKey17": 457,
    "DataCardKey18": 496,
    "DataCardKey19": 462,
    "DataCardKey2": 378,
    "DataCardKey20": 501,
    "DataCardKey21": 108,
    "DataCardKey22": 178,
    "DataCardKey23": 507,
    "DataCardKey26": 395,
    "DataCardKey27": 183,
    "DataCardKey28": 330,
    "DataCardKey3": 73,
    "DataCardKey30": 135,
    "DataCardKey31": 142,
    "DataCardKey32": 146,
    "DataCardKey33": 187,
    "DataCardKey34": 366,
    "DataCardKey36": 371,
    "DataCardKey37": 382,
    "DataCardKey38": 387,
    "DataCardKey4": 78,
    "DataCardKey40": 151,
    "DataCardKey41": 157,
    "DataCardKey42": 294,
    "DataCardKey43": 300,
    "DataCardKey44": 307,
    "DataCardKey45": 312,
    "DataCardKey46": 317,
    "DataCardKey48": 168,
    "DataCardKey49": 163,
    "DataCardKey5": 84,
    "DataCardKey50": 173,
    "DataCardKey56": 348,
    "DataCardKey57": 352,
    "DataCardKey6": 326,
    "DataCardKey7": 94,
    "DataCardKey8": 103,
    "DataCardKey9": 88,
    "DataCardValue10": 463,
    "DataCardValue11": 458,
    "DataCardValue12": 502,
    "DataCardValue13": 179,
    "DataCardValue18": 184,
    "DataCardValue2": 392,
    "DataCardValue20": 188,
    "DataCardValue26": 136,
    "DataCardValue29": 152,
    "DataCardValue3": 323,
    "DataCardValue30": 158,
    "DataCardValue32": 349,
    "DataCardValue33": 353,
    "DataCardValue35": 383,
    "DataCardValue36": 388,
    "DataCardValue38": 169,
    "DataCardValue4": 327,
    "DataCardValue40": 295,
    "DataCardValue41": 301,
    "DataCardValue42": 308,
    "DataCardValue43": 313,
    "DataCardValue44": 318,
    "DataCardValue46": 174,
    "DataCardValue6": 453,
    "DataCardValue7": 109,
    "DataCardValue8": 492,
    "DataCardValue9": 497,
    "DataTable2": 419,
    "DataTableFahrten": 413,
    "DateValue1": 508,
    "Datum_Column1": 420,
    "Datum_DataCard1": 65,
    "Datum_DataCard2": 504,
    "Datum_DataCard3": 364,
    "Datum_DataCard4": 291,
    "Datum_DataCard7": 133,
    "DatumInput": 66,
    "Dropdown4": 302,
    "EndDatePicker": 236,
    "EndDatePicker_1": 260,
    "Ende_Column1": 416,
    "Ende_DataCard1": 75,
    "Ende_DataCard4": 144,
    "EndeInput": 76,
    "EndTimePicker": 235,
    "EndTimePicker_1": 259,
    "errorDatum": 368,
    "ErrorMessage1": 324,
    "ErrorMessage10": 100,
    "ErrorMessage12": 454,
    "ErrorMessage13": 459,
    "ErrorMessage14": 189,
    "ErrorMessage15": 354,
    "ErrorMessage16": 110,
    "ErrorMessage17": 180,
    "ErrorMessage18": 493,
    "ErrorMessage19": 498,
    "ErrorMessage2": 69,
    "ErrorMessage20": 464,
    "ErrorMessage21": 503,
    "ErrorMessage24": 398,
    "ErrorMessage25": 333,
    "ErrorMessage3": 74,
    "ErrorMessage30": 138,
    "ErrorMessage32": 143,
    "ErrorMessage33": 148,
    "ErrorMessage34": 374,
    "ErrorMessage35": 384,
    "ErrorMessage36": 389,
    "ErrorMessage37": 154,
    "ErrorMessage38": 160,
    "ErrorMessage39": 170,
    "ErrorMessage4": 79,
    "ErrorMessage40": 297,
    "ErrorMessage41": 304,
    "ErrorMessage42": 309,
    "ErrorMessage43": 314,
    "ErrorMessage44": 319,
    "ErrorMessage45": 165,
    "ErrorMessage46": 175,
    "ErrorMessage5": 85,
    "ErrorMessage6": 379,
    "ErrorMessage7": 96,
    "ErrorMessage8": 105,
    "ErrorMessage9": 91,
    "Fahrdatum_Column1": 414,
    "Fahrer_DataCard1": 92,
    "Fahrer_DataCard4": 161,
    "FahrerInput": 95,
    "FahrtenDetails": 0,
    "Form1": 64,
    "Form2": 449,
    "Form3": 290,
    "Form4": 363,
    "Form5": 488,
    "Form6": 132,
    "FormViewer2": 346,
    "Gallery1": 274,
    "Gallery2": 472,
    "Gallery3": 444,
    "galleryTemplate1": 275,
    "galleryTemplate1_1": 202,
    "galleryTemplate2": 119,
    "galleryTemplate2_1": 205,
    "galleryTemplate3": 473,
    "galleryTemplate3_1": 213,
    "galleryTemplate4": 445,
    "Geändert am_DataCard2": 182,
    "Geändert am_DataCard3": 347,
    "Geändert von_DataCard3": 185,
    "Geändert von_DataCard4": 350,
    "Group3": 195,
    "GroupHeader": 116,
    "GroupHeader_1": 131,
    "GroupHeader_10": 513,
    "GroupHeader_2": 63,
    "GroupHeader_3": 273,
    "GroupHeader_4": 471,
    "GroupHeader_5": 362,
    "GroupHeader_6": 227,
    "GroupHeader_7": 429,
    "GroupHeader_8": 247,
    "GroupHeader_9": 481,
    "GroupHeader4": 404,
    "GroupHeaderStart": 2,
    "grpBelegBildGross": 288,
    "grpFehler": 228,
    "grpFehler_1": 248,
    "grpHeader": 287,
    "grpSicherheitsabfrage": 289,
    "grpWarnungLoeschen": 249,
    "Gruppe_DataCard1": 97,
    "Gruppe_DataCard3": 380,
    "Gruppe_DataCard4": 310,
    "Gruppe_DataCard6": 166,
    "GruppeInput": 99,
    "icoBusy": 208,
    "icoError": 262,
    "Icon1": 428,
    "Icon1_1": 194,
    "Icon10": 4,
    "Icon2": 122,
    "Icon3": 8,
    "Icon4": 237,
    "Icon5": 279,
    "Icon7": 469,
    "Icon8": 483,
    "Icon9": 54,
    "iconArt": 337,
    "iconCompress": 356,
    "iconEnlarge": 355,
    "iconNextMonth1": 199,
    "iconPrevMonth1": 197,
    "icoSelected": 207,
    "icoStart": 209,
    "Image11": 196,
    "Image13": 6,
    "Image15": 278,
    "Image24": 396,
    "Image26": 331,
    "Image5_1": 19,
    "Image5_2": 14,
    "Image5_3": 24,
    "Image5_5": 29,
    "Image5_6": 34,
    "Image5_7": 39,
    "Image5_8": 44,
    "Image5_9": 49,
    "Image7": 3,
    "Image7_1": 403,
    "Image9": 215,
    "Index_DataCard1": 320,
    "Index_DataCard3": 494,
    "inpEnde": 147,
    "inpFahrer": 164,
    "inpStart": 140,
    "InputArt": 376,
    "InputBetrag": 372,
    "InputDatum": 367,
    "KMKosten": 406,
    "Kommentar_DataCard1": 101,
    "Kommentar_DataCard3": 171,
    "KommentarInput": 104,
    "Konto": 0,
    "Kontostand": 411,
    "Kosten_Column1": 418,
    "Kosten_DataCard1": 86,
    "Kosten_DataCard4": 155,
    "labBuchungGruppe": 230,
    "labBuchungGruppe_1": 251,
    "labDay": 206,
    "Label1": 433,
    "Label1_1": 217,
    "Label1_3": 219,
    "Label10": 286,
    "Label11": 515,
    "Label12": 254,
    "Label12_1": 257,
    "Label13": 82,
    "Label13_1": 90,
    "Label14": 1,
    "Label15": 5,
    "Label15_1": 117,
    "Label15_2": 514,
    "Label16": 261,
    "Label17": 338,
    "Label18": 296,
    "Label19": 241,
    "Label2": 436,
    "Label20": 292,
    "Label21": 303,
    "Label22": 405,
    "Label23": 137,
    "Label24": 153,
    "Label25": 159,
    "Label25_2": 410,
    "Label26": 200,
    "Label27": 339,
    "Label28": 340,
    "Label28_1": 341,
    "Label29": 238,
    "Label3": 432,
    "Label30": 484,
    "Label31": 485,
    "Label32": 486,
    "Label33": 487,
    "Label34": 516,
    "Label38": 266,
    "Label4": 439,
    "Label5": 435,
    "Label6": 438,
    "Label7": 475,
    "Label7_1": 442,
    "Label8": 55,
    "Label8_2": 430,
    "Label8_3": 431,
    "Label9": 56,
    "labEnde": 234,
    "labEnde_1": 258,
    "labError": 263,
    "labGruppe": 229,
    "labGruppe_1": 250,
    "labKMStand": 7,
    "labKMStand_1": 10,
    "labKosten": 89,
    "labStart": 231,
    "labStart_1": 252,
    "labStrecke": 81,
    "labVersion": 58,
    "labVersion_1": 111,
    "labVersion_10": 441,
    "labVersion_11": 466,
    "labVersion_12": 478,
    "labVersion_13": 509,
    "labVersion_14": 520,
    "labVersion_2": 126,
    "labVersion_3": 222,
    "labVersion_4": 240,
    "labVersion_5": 268,
    "labVersion_6": 282,
    "labVersion_7": 357,
    "labVersion_8": 399,
    "labVersion_9": 424,
    "LblAppName1": 192,
    "LblAppName2": 113,
    "LblAppName2_1": 470,
    "LblAppName2_10": 226,
    "LblAppName2_11": 246,
    "LblAppName2_2": 482,
    "LblAppName2_3": 129,
    "LblAppName2_4": 62,
    "LblAppName2_5": 271,
    "LblAppName2_6": 511,
    "LblAppName2_7": 361,
    "LblAppName2_8": 402,
    "LblAppName2_9": 427,
    "LblCalendarEventsHeader1": 211,
    "LblMonthSelected1": 198,
    "LblNoEvents1": 221,
    "MonthDayGallery1": 204,
    "Name_DataCard1": 325,
    "Name_DataCard2": 450,
    "Name_DataCard3": 390,
    "NeueAusgabe": 0,
    "NeueFahrt": 0,
    "Ort_Column1": 423,
    "Ort_DataCard3": 385,
    "Ort_DataCard4": 315,
    "popupVersionsupdate": 53,
    "recHintergrund": 336,
    "Rectangle1": 123,
    "Rectangle2": 434,
    "Rectangle2_1": 437,
    "Rectangle2_2": 440,
    "Rectangle3": 0,
    "Rectangle4": 283,
    "Rectangle5": 253,
    "Rectangle6": 334,
    "Rectangle7": 52,
    "Rectangle8": 9,
    "RectCalendarEventsHeader1": 210,
    "RectQuickActionBar1": 191,
    "RectQuickActionBar2": 112,
    "RectQuickActionBar2_1": 467,
    "RectQuickActionBar2_10": 243,
    "RectQuickActionBar2_11": 479,
    "RectQuickActionBar2_2": 127,
    "RectQuickActionBar2_3": 59,
    "RectQuickActionBar2_4": 269,
    "RectQuickActionBar2_5": 510,
    "RectQuickActionBar2_6": 358,
    "RectQuickActionBar2_7": 400,
    "RectQuickActionBar2_8": 425,
    "RectQuickActionBar2_9": 223,
    "ScreenBuchungAendern": 0,
    "ScreenFahrzeug": 0,
    "ScreenKalender": 0,
    "ScreenNeueBuchung": 0,
    "ScreenNeueBuchungDoku": 0,
    "ScreenVersionen": 0,
    "ScreenVersionenNeu": 0,
    "Separator1": 345,
    "Separator1_1": 190,
    "Separator2": 281,
    "Separator3": 125,
    "Separator3_1": 220,
    "Separator4": 448,
    "Separator5": 505,
    "Separator6": 477,
    "Settings": 0,
    "Start": 0,
    "Start_Column1": 415,
    "Start_DataCard1": 70,
    "Start_DataCard4": 139,
    "StartDatePicker": 232,
    "StartDatePicker_1": 255,
    "StartInput": 71,
    "StartTimePicker": 233,
    "StartTimePicker_1": 256,
    "StarVisible1": 87,
    "StarVisible10": 451,
    "StarVisible11": 456,
    "StarVisible12": 186,
    "StarVisible13": 351,
    "StarVisible14": 107,
    "StarVisible15": 177,
    "StarVisible16": 490,
    "StarVisible17": 495,
    "StarVisible18": 461,
    "StarVisible19": 500,
    "StarVisible2": 321,
    "StarVisible20": 506,
    "StarVisible23": 394,
    "StarVisible24": 329,
    "StarVisible29": 134,
    "StarVisible3": 72,
    "StarVisible3_2": 67,
    "StarVisible3_3": 293,
    "StarVisible3_4": 299,
    "StarVisible3_5": 306,
    "StarVisible3_6": 365,
    "StarVisible3_8": 370,
    "StarVisible30": 141,
    "StarVisible31": 145,
    "StarVisible32": 381,
    "StarVisible33": 386,
    "StarVisible35": 150,
    "StarVisible36": 156,
    "StarVisible37": 167,
    "StarVisible38": 162,
    "StarVisible39": 172,
    "StarVisible4": 77,
    "StarVisible40": 311,
    "StarVisible41": 316,
    "StarVisible5": 83,
    "StarVisible6": 377,
    "StarVisible7": 93,
    "StarVisible8": 102,
    "Statistiken": 0,
    "Strecke_Column1": 417,
    "Strecke_DataCard1": 80,
    "Strecke_DataCard4": 149,
    "Subtitle2": 280,
    "Subtitle3": 121,
    "Subtitle3_1": 216,
    "Subtitle3_2": 218,
    "Subtitle4": 447,
    "Subtitle5": 476,
    "TextInput2": 517,
    "TextInput3": 373,
    "Title1": 203,
    "Title2": 276,
    "Title3": 120,
    "Title4": 446,
    "Title5": 474,
    "Title7": 214,
    "version_DataCard1": 489,
    "ViewAenderungsdaten": 181,
    "WeekdayGallery1": 201,
    "Wert_DataCard1": 460
  },
  "ResourcesJsonIndices": {
    "Image-001-wallet": 11,
    "Image-002-accounting": 6,
    "Image-002-money-transfer": 7,
    "Image-003-car-wash": 9,
    "Image-004-maintenance": 8,
    "Image-005-parking": 10,
    "Image-006-calendar": 13,
    "Image-007-calendar-1": 15,
    "Image-bg ford 812": 1,
    "Image-car-driver blau": 14,
    "Image-car-statistics": 3,
    "Image-car-wheel": 16,
    "Image-checkout-logo-150x32-alt-2x": 12,
    "Image-datei": 17,
    "Image-gas-station": 5,
    "Image-ico_alleausgaben": 18,
    "Image-ico_allefahrten": 19,
    "Image-ico_buchenNeu": 21,
    "Image-ico_fahrerin": 25,
    "Image-ico_fahrten": 22,
    "Image-ico_fahrzeug": 26,
    "Image-ico_konto": 23,
    "Image-ico_neueausgaben": 20,
    "Image-ico_stats": 24,
    "Image-marketing": 4,
    "Image-riding-car": 2,
    "Image-SampleImage": 0
  },
  "TemplateVersions": {},
  "VolatileProperties": {
    "AnalysisLoadTime": 5.0069149,
    "ControlCount": {
      "addMedia": 2,
      "button": 45,
      "circle": 2,
      "combobox": 3,
      "dataTable": 2,
      "dataTableColumn": 9,
      "datepicker": 9,
      "dropdown": 5,
      "form": 6,
      "formViewer": 2,
      "gallery": 7,
      "galleryTemplate": 7,
      "group": 21,
      "groupContainer": 25,
      "icon": 15,
      "image": 19,
      "label": 230,
      "rectangle": 32,
      "screen": 17,
      "text": 35,
      "typedDataCard": 44
    },
    "DeserializationLoadTime": 8.7994195,
    "ErrorCount": 0
  }
}